resourceComponents/__init__.py
resourceComponents/aks.py
resourceComponents/application.py
resourceComponents/bootstrap.py
resourceComponents/hub.py
resourceComponents/sentinel.py
resourceComponents/spoke.py
resourceComponents/virtual_machine.py
resources/__init__.py
resources/azure_ad.py
resources/bastion_hosts.py
resources/compute.py
resources/container_service.py
resources/expressroute_gateway.py
resources/firewall.py
resources/key_vault.py
resources/log_analytics.py
resources/operational_insights.py
resources/resource_group.py
resources/route_table.py
resources/security_insights.py
resources/storage_account.py
resources/vnet.py
resources/vpn_gateway.py
xangobolt_pulumi_azure-0.0.3.dist-info/LICENSE
xangobolt_pulumi_azure-0.0.3.dist-info/METADATA
xangobolt_pulumi_azure-0.0.3.dist-info/WHEEL
xangobolt_pulumi_azure-0.0.3.dist-info/top_level.txt
xangobolt_pulumi_azure-0.0.3.dist-info/RECORD
